{
  "name": "No Gyro",
  "width": 629,
  "height": 605,
  "version": 1,
  "children": [
    {
      "type": "image",
      "image": "base.png",
      "x": 314.5,
      "y": 302.5,
      "width": 629.0,
      "height": 605.0,
      "center": true,
      "children": [
        {
          "x": 74.0,
          "y": 67.0,
          "children": [
            {
              "type": "showhide",
              "input": "quad_right:s",
              "children": [
                {
                  "type": "image",
                  "image": "btn-face.png",
                  "x": 0.0,
                  "y": 35.0,
                  "width": 36.0,
                  "height": 36.0,
                  "center": true
                }
              ]
            },
            {
              "type": "showhide",
              "input": "quad_right:e",
              "children": [
                {
                  "type": "image",
                  "image": "btn-face.png",
                  "x": 35.0,
                  "y": 0.0,
                  "width": 36.0,
                  "height": 36.0,
                  "center": true
                }
              ]
            },
            {
              "type": "showhide",
              "input": "quad_right:w",
              "children": [
                {
                  "type": "image",
                  "image": "btn-face.png",
                  "x": -35.0,
                  "y": 0.0,
                  "width": 36.0,
                  "height": 36.0,
                  "center": true
                }
              ]
            },
            {
              "type": "showhide",
              "input": "quad_right:n",
              "children": [
                {
                  "type": "image",
                  "image": "btn-face.png",
                  "x": 0.0,
                  "y": -35.0,
                  "width": 36.0,
                  "height": 36.0,
                  "center": true
                }
              ]
            }
          ]
        },
        {
          "type": "showhide",
          "input": "stick_left:click",
          "children": [
            {
              "type": "image",
              "image": "btn-stick.png",
              "x": -73.0,
              "y": 67.0,
              "width": 105.0,
              "height": 105.0,
              "center": true
            }
          ]
        },
        {
          "type": "slider",
          "x": -72.0,
          "y": 67.0,
          "inputX": "stick_left:x * 16",
          "inputY": "stick_left:y * 16",
          "children": [
            {
              "type": "image",
              "image": "stick.png",
              "x": 0.0,
              "y": 0.0,
              "width": 69.0,
              "height": 70.0,
              "center": true
            }
          ]
        },
        {
          "x": 0.0,
          "y": -29.0,
          "children": [
            {
              "type": "showhide",
              "input": "home",
              "children": [
                {
                  "type": "image",
                  "image": "btn-home.png",
                  "x": 0.0,
                  "y": -8.0,
                  "width": 51.0,
                  "height": 51.0,
                  "center": true
                }
              ]
            },
            {
              "type": "showhide",
              "input": "menu:r",
              "children": [
                {
                  "type": "image",
                  "image": "btn-sub.png",
                  "x": 52.0,
                  "y": 0.0,
                  "width": 38.0,
                  "height": 22.0,
                  "center": true
                }
              ]
            },
            {
              "type": "showhide",
              "input": "menu:l",
              "children": [
                {
                  "type": "image",
                  "image": "btn-sub.png",
                  "x": -52.0,
                  "y": 0.0,
                  "width": 38.0,
                  "height": 22.0,
                  "center": true
                }
              ]
            }
          ]
        },
        {
          "x": 0.0,
          "y": -235.0,
          "children": [
            {
              "type": "showhide",
              "input": "grip:l",
              "children": [
                {
                  "type": "image",
                  "image": "btn-trigger.png",
                  "x": -75.0,
                  "y": 0.0,
                  "width": 50.0,
                  "height": 50.0,
                  "center": true
                }
              ]
            },
            {
              "type": "showhide",
              "input": "triggers:l:stage2",
              "children": [
                {
                  "type": "image",
                  "image": "btn-trigger.png",
                  "x": -163.0,
                  "y": 48.0,
                  "width": 50.0,
                  "height": 50.0,
                  "center": true
                }
              ]
            },
            {
              "type": "showhide",
              "input": "bumpers:l",
              "children": [
                {
                  "type": "image",
                  "image": "btn-trigger.png",
                  "x": -163.0,
                  "y": -28.0,
                  "width": 50.0,
                  "height": 50.0,
                  "center": true
                }
              ]
            },
            {
              "type": "showhide",
              "input": "grip:r",
              "children": [
                {
                  "type": "image",
                  "image": "btn-trigger.png",
                  "x": 75.0,
                  "y": 0.0,
                  "width": 50.0,
                  "height": 50.0,
                  "center": true
                }
              ]
            },
            {
              "type": "showhide",
              "input": "triggers:r:stage2",
              "children": [
                {
                  "type": "image",
                  "image": "btn-trigger.png",
                  "x": 163.0,
                  "y": 48.0,
                  "width": 50.0,
                  "height": 50.0,
                  "center": true
                }
              ]
            },
            {
              "type": "showhide",
              "input": "bumpers:r",
              "children": [
                {
                  "type": "image",
                  "image": "btn-trigger.png",
                  "x": 163.0,
                  "y": -28.0,
                  "width": 50.0,
                  "height": 50.0,
                  "center": true
                }
              ]
            }
          ]
        },
        {
          "type": "showhide",
          "input": "touch_right:click",
          "children": [
            {
              "type": "image",
              "image": "btn-haptic.png",
              "x": 171.0,
              "y": -23.0,
              "width": 156.0,
              "height": 160.0,
              "center": true
            }
          ]
        },
        {
          "x": 171.0,
          "y": -23.0,
          "children": [
            {
              "type": "trailpad",
              "image": "padheat.png",
              "x": 0.0,
              "y": 0.0,
              "width": 36.0,
              "height": 36.0,
              "input": "touch_right:0:touch",
              "inputX": "touch_right:0:x * 72",
              "inputY": "touch_right:0:y * 72",
              "length": 30,
              "children": [
                {
                  "type": "showhide",
                  "input": "touch_right:0:touch",
                  "children": [
                    {
                      "type": "image",
                      "image": "btn-face.png",
                      "x": 0.0,
                      "y": 0.0,
                      "width": 36.0,
                      "height": 36.0,
                      "center": true
                    }
                  ]
                }
              ]
            }
          ]
        },
        {
          "type": "showhide",
          "input": "touch_left:click",
          "children": [
            {
              "type": "image",
              "image": "btn-haptic.png",
              "x": -171.0,
              "y": -23.0,
              "width": 156.0,
              "height": 160.0,
              "center": true
            }
          ]
        },
        {
          "x": -171.0,
          "y": -23.0,
          "children": [
            {
              "type": "trailpad",
              "image": "padheat.png",
              "x": 0.0,
              "y": 0.0,
              "width": 36.0,
              "height": 36.0,
              "input": "touch_left:0:touch",
              "inputX": "touch_left:0:x * 72",
              "inputY": "touch_left:0:y * 72",
              "length": 30,
              "children": [
                {
                  "type": "showhide",
                  "input": "touch_left:0:touch",
                  "children": [
                    {
                      "type": "image",
                      "image": "btn-face.png",
                      "x": 0.0,
                      "y": 0.0,
                      "width": 36.0,
                      "height": 36.0,
                      "center": true
                    }
                  ]
                }
              ]
            }
          ]
        },
        {
          "x": 0.0,
          "y": -170.0,
          "children": [
            {
              "type": "pbar",
              "x": -65.0,
              "y": 0.0,
              "width": 120.0,
              "height": 15.0,
              "center": true,
              "input": "triggers:l:analog",
              "direction": "right",
              "min": "0",
              "max": "1",
              "foreground": "ff000000",
              "background": "ffffffff"
            },
            {
              "type": "pbar",
              "x": 65.0,
              "y": 0.0,
              "width": 120.0,
              "height": 15.0,
              "center": true,
              "input": "triggers:r:analog",
              "direction": "left",
              "min": "0",
              "max": "1",
              "foreground": "ff000000",
              "background": "ffffffff"
            }
          ]
        }
      ]
    }
  ]
}